{
  "cols": [
    [
      {
        "label": "About",
        "url": "https://eosc-portal.eu/about-eosc-portal",
        "navBtns": [
          {
            "label": "EOSC",
            "url": "https://eosc-portal.eu/about/eosc"
          },
          {
            "label": "EOSC Portal",
            "url": "https://eosc-portal.eu/about-eosc-portal"
          },
          {
            "label": "EOSC Doers",
            "url": "https://eosc-portal.eu/about/eosc-doers"
          },
          {
            "label": "EOSC Glossary",
            "url": "https://eosc-portal.eu/glossary"
          },
          {
            "label": "EOSC Projects",
            "url": "https://eosc-portal.eu/about/eosc-projects"
          },
          {
            "label": "EOSC Governance",
            "url": "https://eosc-portal.eu/governance"
          },
          {
            "label": "EOSC Portal FAQs",
            "url": "https://eosc-portal.eu/about/faqs"
          },
          {
            "label": "EOSC Association",
            "url": "https://eosc.eu/"
          },
          {
            "label": "EOSC Enhance",
            "url": "https://eosc-portal.eu/enhance"
          }
        ]
      }
    ],
    [
      {
        "label": "Use Cases",
        "navBtns": [
          {
            "label": "Community Use Cases",
            "url": "https://eosc-portal.eu/eosc-in-practice/use-cases"
          },
          {
            "label": "Submit Use Case",
            "url": "https://eosc-portal.eu/eosc-in-practice/open-call"
          },
          {
            "label": "Industry Use Case",
            "url": "https://eosc-portal.eu/industry-use-cases"
          }
        ]
      },
      {
        "label": "For providers",
        "url": "https://eosc-portal.eu/for-providers",
        "navBtns": [
          {
            "label": "Providers Documentation",
            "url": "https://eosc-portal.eu/providers-documentation"
          },
          {
            "label": "Promote your services",
            "url": "https://www.eosc-portal.eu/contribute-promotional-article-your-service"
          }
        ]
      }
    ],
    [
      {
        "label": "Services & Research products",
        "url": "https://eosc-portal.eu/services-resources",
        "navBtns": [
          {
            "label": "Manage Research Data",
            "url": "https://search.eosc-portal.eu/search/all?q=*&fq=unified_categories:(%22Manage%20Research%20Data%22)"
          },
          {
            "label": "Access Computing and Storage Resources",
            "url": "https://search.eosc-portal.eu/search/all?q=*&fq=unified_categories:(%22Access%20Computing%20and%20Storage%20Resources%22)"
          },
          {
            "label": "Access Research Infrastructures",
            "url": "https://search.eosc-portal.eu/search/all?q=*&fq=unified_categories:(%22Access%20Research%20Infrastructures%22)"
          },
          {
            "label": "Access Training Material",
            "url": "https://search.eosc-portal.eu/search/all?q=*&fq=unified_categories:(%22Access%20Training%20Material%22)"
          },
          {
            "label": "Find Bundles",
            "url": "https://search.eosc-portal.eu/search/all?q=*&fq=unified_categories:(%22Find%20Bundles%22)"
          },
          {
            "label": "Find Instruments & Equipment",
            "url": "https://search.eosc-portal.eu/search/all?q=*&fq=unified_categories:(%22Find%20Instruments%20%5C%26%20Equipment%22)"
          },
          {
            "label": "Process and Analyse",
            "url": "https://search.eosc-portal.eu/search/all?q=*&fq=unified_categories:(%22Process%20and%20Analyse%22)"
          },
          {
            "label": "Publish Research Outputs",
            "url": "https://search.eosc-portal.eu/search/all?q=*&fq=unified_categories:(%22Publish%20Research%20Outputs%22)"
          }
        ]
      }
    ],
    [
      {
        "label": "Media",
        "navBtns": [
          {
            "label": "News",
            "url": "https://eosc-portal.eu/media/news"
          },
          {
            "label": "Forthcoming events",
            "url": "https://eosc-portal.eu/media/events"
          },
          {
            "label": "Past events",
            "url": "https://eosc-portal.eu/media/past-events"
          },
          {
            "label": "Submit your News/Event",
            "url": "https://eosc-portal.eu/contribute-to-eosc"
          },
          {
            "label": "Community",
            "url": "https://eosc-portal.eu/documents/community"
          },
          {
            "label": "Newsletters",
            "url": "https://eosc-portal.eu/newsletters"
          }
        ]
      }
    ],
    [
      {
        "label": "Using the portal",
        "url": "https://eosc-portal.eu/using-the-portal",
        "navBtns": [
          {
            "label": "EOSC Portal FAQs",
            "url": "https://eosc-portal.eu/about/faqs"
          },
          {
            "type": "termsOfUse",
            "label": "Term of use"
          }
        ]
      },
      {
        "label": "Policy",
        "navBtns": [
          {
            "label": "EC Documents",
            "url": "https://eosc-portal.eu/documents/ec-documents"
          },
          {
            "label": "EU+ Countries",
            "url": "https://eosc-portal.eu/policy/eu-member-states"
          },
          {
            "label": "European Union",
            "url": "https://eosc-portal.eu/policy/eu-member-states"
          },
          {
            "type": "privacyPolicy",
            "label": "Privacy Policy"
          }
        ]
      }
    ]
  ],
  "socials": [
    {
      "class": "social-logo twitter-logo d-inline-block mr-2",
      "url": "https://twitter.com/EoscPortal"
    },
    {
      "class": "social-logo yt-logo d-inline-block",
      "url": "https://www.youtube.com/channel/UCHsaUFy5LJ3rJ28qDg2StGA"
    }
  ]
}
